losia/__init__.py
losia/optimizer.py
losia/losia_torch/__init__.py
losia/losia_torch/adamw.py
losia/losia_torch/index_select_dim2.cu
losia/losia_torch/losia_projector_cuda.py
losia/losia_torch/scheduler.py
losia/losia_torch/strategy.py
losia/peft_training/__init__.py
losia/peft_training/args_utils.py
losia/peft_training/dataloader.py
losia/peft_training/losia_pro.py
losia/peft_training/training_utils.py
losia-0.1.5.dist-info/LICENSE
losia-0.1.5.dist-info/METADATA
losia-0.1.5.dist-info/WHEEL
losia-0.1.5.dist-info/top_level.txt
losia-0.1.5.dist-info/RECORD
