Metadata-Version: 2.1
Name: losia
Version: 0.1.5
Summary: An resource-efficient fine-tuning toolkit that tunes model via subnet-structured optimization, localization, and integration.
Home-page: https://github.com/KlozeWang/LoSiA
Author: Xujia Wang
Author-email: wang-xj22@mails.tsinghua.edu.cn
License: Apache-2.0
Classifier: Programming Language :: Python :: 3
Classifier: License :: OSI Approved :: Apache Software License
Classifier: Operating System :: OS Independent
Requires-Python: >=3.8
License-File: LICENSE
Requires-Dist: bitsandbytes
Requires-Dist: datasets
Requires-Dist: loguru
Requires-Dist: matplotlib
Requires-Dist: numpy
Requires-Dist: tensorly
Requires-Dist: torch
Requires-Dist: tqdm
Requires-Dist: transformers
Requires-Dist: ninja
